dkdc_crypto/__init__.py
dkdc_crypto/main.py
dkdc_crypto-0.0.2.dist-info/METADATA
dkdc_crypto-0.0.2.dist-info/WHEEL
dkdc_crypto-0.0.2.dist-info/top_level.txt
dkdc_crypto-0.0.2.dist-info/RECORD
